gen_efi_app/__init__.py
gen_efi_app/py.typed
gen_efi_app/conf/gen_efi_app.cfg
gen_efi_app/conf/gen_efi_app.logo
gen_efi_app/conf/gen_efi_app_util.cfg
gen_efi_app/conf/project.yaml
gen_efi_app/conf/template/cflags.template
gen_efi_app/conf/template/ldflags.template
gen_efi_app/conf/template/main.template
gen_efi_app/conf/template/makefile.template
gen_efi_app/conf/template/objects.template
gen_efi_app/conf/template/ocflags.template
gen_efi_app/log/gen_efi_app.log
gen_efi_app/pro/__init__.py
gen_efi_app/pro/read_template.py
gen_efi_app/pro/write_template.py
usr/local/bin/gen_efi_app_run.py
gen_efi_app-1.3.4.dist-info/LICENSE
gen_efi_app-1.3.4.dist-info/METADATA
gen_efi_app-1.3.4.dist-info/WHEEL
gen_efi_app-1.3.4.dist-info/top_level.txt
gen_efi_app-1.3.4.dist-info/RECORD
